sbb_binarize/__init__.py
sbb_binarize/cli.py
sbb_binarize/ocrd-tool.json
sbb_binarize/ocrd_cli.py
sbb_binarize/sbb_binarize.py
sbb_binarization-0.1.0.dist-info/LICENSE
sbb_binarization-0.1.0.dist-info/METADATA
sbb_binarization-0.1.0.dist-info/WHEEL
sbb_binarization-0.1.0.dist-info/entry_points.txt
sbb_binarization-0.1.0.dist-info/top_level.txt
sbb_binarization-0.1.0.dist-info/RECORD
