Metadata-Version: 2.1
Name: sbb-binarization
Version: 0.1.0
Summary: Pixelwise binarization with selectional auto-encoders in Keras
Home-page: https://github.com/qurator-spk/sbb_binarization
Author: Vahid Rezanezhad
License: Apache License 2.0
License-File: LICENSE
Requires-Dist: numpy
Requires-Dist: setuptools (>=41)
Requires-Dist: opencv-python-headless
Requires-Dist: ocrd (>=2.38.0)
Requires-Dist: tensorflow (>=2.4.0)
